hf_endpoints_emulator/__init__.py
hf_endpoints_emulator/cli.py
hf_endpoints_emulator/emulator.py
hf_endpoints_emulator/serializer_deserializer.py
hf_endpoints_emulator-0.1.1.dist-info/LICENSE
hf_endpoints_emulator-0.1.1.dist-info/METADATA
hf_endpoints_emulator-0.1.1.dist-info/WHEEL
hf_endpoints_emulator-0.1.1.dist-info/entry_points.txt
hf_endpoints_emulator-0.1.1.dist-info/top_level.txt
hf_endpoints_emulator-0.1.1.dist-info/RECORD
