Metadata-Version: 2.1
Name: hf-endpoints-emulator
Version: 0.1.1
Summary: Emulator for Custom Handlers for Inference Endpoints
Home-page: https://huggingface.co/inference-endpoints
Author: HuggingFace
License: MIT
Keywords: NLP deep-learning transformer pytorch tensorflow BERT GPT GPT-2
Classifier: Development Status :: 5 - Production/Stable
Classifier: Intended Audience :: Developers
Classifier: Intended Audience :: Education
Classifier: Intended Audience :: Science/Research
Classifier: License :: OSI Approved :: Apache Software License
Classifier: Operating System :: OS Independent
Classifier: Programming Language :: Python :: 3
Classifier: Programming Language :: Python :: 3.9
Classifier: Topic :: Scientific/Engineering :: Artificial Intelligence
Requires-Python: >=3.8.0
License-File: LICENSE
Requires-Dist: Pillow
Requires-Dist: starlette
Requires-Dist: uvicorn
Requires-Dist: typer[all]
Provides-Extra: quality
Requires-Dist: black ; extra == 'quality'
Requires-Dist: isort ; extra == 'quality'
Requires-Dist: flake8 ; extra == 'quality'
Provides-Extra: test
Requires-Dist: pytest ; extra == 'test'
Requires-Dist: pytest-xdist ; extra == 'test'
Requires-Dist: parameterized ; extra == 'test'
Requires-Dist: psutil ; extra == 'test'
Requires-Dist: datasets ; extra == 'test'
Requires-Dist: pytest-sugar ; extra == 'test'
Requires-Dist: mock (==2.0.0) ; extra == 'test'
Requires-Dist: docker ; extra == 'test'
Requires-Dist: requests ; extra == 'test'
